napari_basicpy/__init__.py
napari_basicpy/_sample_data.py
napari_basicpy/_version.py
napari_basicpy/_widget.py
napari_basicpy/napari.yaml
napari_basicpy/_icons/logo.png
napari_basicpy/_tests/__init__.py
napari_basicpy/_tests/test_sample_data.py
napari_basicpy/_tests/test_widget.py
napari_basicpy-0.0.3.dist-info/LICENSE
napari_basicpy-0.0.3.dist-info/METADATA
napari_basicpy-0.0.3.dist-info/WHEEL
napari_basicpy-0.0.3.dist-info/entry_points.txt
napari_basicpy-0.0.3.dist-info/top_level.txt
napari_basicpy-0.0.3.dist-info/RECORD
