Metadata-Version: 2.1
Name: napari-basicpy
Version: 0.0.3
Summary: BaSiCPy illumination correction for napari
Home-page: https://github.com/tdmorello/napari-basicpy
Author: Tim Morello
Author-email: tdmorello@gmail.com
License: BSD-3-Clause
Project-URL: Bug Tracker, https://github.com/peng-lab/napari-basicpy/issues
Project-URL: Documentation, https://github.com/peng-lab/napari-basicpy#README.md
Project-URL: Source Code, https://github.com/peng-lab/napari-basicpy
Project-URL: User Support, https://github.com/peng-lab/napari-basicpy/issues
Classifier: Development Status :: 2 - Pre-Alpha
Classifier: Framework :: napari
Classifier: Intended Audience :: Developers
Classifier: License :: OSI Approved :: BSD License
Classifier: Operating System :: OS Independent
Classifier: Programming Language :: Python
Classifier: Programming Language :: Python :: 3
Classifier: Programming Language :: Python :: 3 :: Only
Classifier: Programming Language :: Python :: 3.8
Classifier: Programming Language :: Python :: 3.9
Classifier: Programming Language :: Python :: 3.10
Classifier: Topic :: Scientific/Engineering :: Image Processing
Requires-Python: >=3.8
License-File: LICENSE
Requires-Dist: basicpy >=1.2.0
Requires-Dist: numpy
Requires-Dist: qtpy
Provides-Extra: dev
Requires-Dist: black ; extra == 'dev'
Requires-Dist: flake8 ; extra == 'dev'
Requires-Dist: flake8-black ; extra == 'dev'
Requires-Dist: flake8-docstrings ; extra == 'dev'
Requires-Dist: flake8-isort ; extra == 'dev'
Requires-Dist: isort ; extra == 'dev'
Requires-Dist: mypy ; extra == 'dev'
Requires-Dist: pre-commit ; extra == 'dev'
Requires-Dist: pydocstyle ; extra == 'dev'
Requires-Dist: pytest ; extra == 'dev'
Requires-Dist: pytest-qt ; extra == 'dev'
Provides-Extra: testing
Requires-Dist: tox ; extra == 'testing'
Requires-Dist: pytest ; extra == 'testing'
Requires-Dist: pytest-cov ; extra == 'testing'
Requires-Dist: pytest-qt ; extra == 'testing'
Requires-Dist: napari ; extra == 'testing'
Provides-Extra: tox-testing
Requires-Dist: tox ; extra == 'tox-testing'
Requires-Dist: pytest ; extra == 'tox-testing'
Requires-Dist: pytest-cov ; extra == 'tox-testing'
Requires-Dist: pytest-qt ; extra == 'tox-testing'
Requires-Dist: napari ; extra == 'tox-testing'
Requires-Dist: pyqt5 ; extra == 'tox-testing'
